[{"name":"ArtScience Museum","type":"Museum","star":4.5,"address":"6 Bayfront Ave","gmap_url":"https:\/\/www.google.com\/maps\/place\/ArtScience+Museum\/data=!4m7!3m6!1s0x31da19042950679d:0x81c847e129eec549!8m2!3d1.2862738!4d103.8592663!16s%2Fm%2F0gff2yr!19sChIJnWdQKQQZ2jERScXuKeFHyIE?authuser=0&hl=en&rclk=1","image_url":"https:\/\/lh5.googleusercontent.com\/p\/AF1QipO01mwxFk1e9YHZgIzkd_fUWSuIAVmivFN1N7-5=w122-h92-k-no"},{"name":"National Museum of Singapore","type":"National museum","star":4.6,"address":"93 Stamford Rd","gmap_url":"https:\/\/www.google.com\/maps\/place\/National+Museum+of+Singapore\/data=!4m7!3m6!1s0x31da19a311be5b0f:0x92e311597c4db868!8m2!3d1.296613!4d103.8485091!16zL20vMGZ5bXp0!19sChIJD1u-EaMZ2jERaLhNfFkR45I?authuser=0&hl=en&rclk=1","image_url":"https:\/\/lh5.googleusercontent.com\/p\/AF1QipMkaruchYehextmCKGnW_Jcsez4lcS4-UgTcs-r=w137-h92-k-no"},{"name":"National Gallery Singapore","type":"Art museum","star":4.6,"address":"Singapore","gmap_url":"https:\/\/www.google.com\/maps\/place\/National+Gallery+Singapore\/data=!4m7!3m6!1s0x31da19a747de0c15:0xe5639e25fabece80!8m2!3d1.2902217!4d103.8515167!16s%2Fm%2F02z3_27!19sChIJFQzeR6cZ2jERgM6--iWeY-U?authuser=0&hl=en&rclk=1","image_url":"https:\/\/lh5.googleusercontent.com\/p\/AF1QipPo9-KW5k6gJwge4ZHQERD2BBDZq0E5BncE0puG=w122-h92-k-no"},{"name":"Peranakan Museum","type":"Museum","star":4.4,"address":"39 Armenian St","gmap_url":"https:\/\/www.google.com\/maps\/place\/Peranakan+Museum\/data=!4m7!3m6!1s0x31da19a3e7fd9559:0xcc80d2cf6e676720!8m2!3d1.2943669!4d103.8490391!16s%2Fm%2F04lhqz0!19sChIJWZX956MZ2jERIGdnbs_SgMw?authuser=0&hl=en&rclk=1","image_url":"https:\/\/lh5.googleusercontent.com\/p\/AF1QipMjibhmQ54dk0U4cw1Uom1gpWfGSgZiFj7EtTmi=w115-h92-k-no"},{"name":"Children Little Museum","type":"Toy museum","star":4.2,"address":"Singapore","gmap_url":"https:\/\/www.google.com\/maps\/place\/Children+Little+Museum\/data=!4m7!3m6!1s0x31da19b106165e09:0xca5059f9956e2910!8m2!3d1.302714!4d103.8606303!16s%2Fg%2F1tcw5q9c!19sChIJCV4WBrEZ2jEREClulflZUMo?authuser=0&hl=en&rclk=1","image_url":"https:\/\/lh5.googleusercontent.com\/p\/AF1QipO4SPTSwn8dKFdhmYSqyAufdK640hGW3MKyGzGs=w122-h92-k-no"},{"name":"Children Little Museum","type":"Toy museum","star":4.2,"address":"Singapore","gmap_url":"https:\/\/www.google.com\/maps\/place\/Children+Little+Museum\/data=!4m7!3m6!1s0x31da19b106165e09:0xca5059f9956e2910!8m2!3d1.302714!4d103.8606303!16s%2Fg%2F1tcw5q9c!19sChIJCV4WBrEZ2jEREClulflZUMo?authuser=0&hl=en&rclk=1","image_url":"https:\/\/lh5.googleusercontent.com\/p\/AF1QipO4SPTSwn8dKFdhmYSqyAufdK640hGW3MKyGzGs=w122-h92-k-no"},{"name":"Asian Civilisations Museum","type":"Heritage museum","star":4.6,"address":"1 Empress Pl","gmap_url":"https:\/\/www.google.com\/maps\/place\/Asian+Civilisations+Museum\/data=!4m7!3m6!1s0x31da190999a193a1:0x20a06ca9bcdf127a!8m2!3d1.2874969!4d103.8513861!16zL20vMDZfOG1u!19sChIJoZOhmQkZ2jERehLfvKlsoCA?authuser=0&hl=en&rclk=1","image_url":"https:\/\/lh5.googleusercontent.com\/p\/AF1QipP8RA-y1IxMSYTSkBjwxVZPV14RZL0jeCAa3HZ4=w122-h92-k-no"},{"name":"Science Centre Singapore","type":"Science museum","star":4.4,"address":"15 Science Centre Rd","gmap_url":"https:\/\/www.google.com\/maps\/place\/Science+Centre+Singapore\/data=!4m7!3m6!1s0x31da1004147cad63:0x18e02380e45f8dce!8m2!3d1.3331687!4d103.7356443!16zL20vMDZfOGJ0!19sChIJY618FAQQ2jERzo1f5IAj4Bg?authuser=0&hl=en&rclk=1","image_url":"https:\/\/lh5.googleusercontent.com\/p\/AF1QipM8dKALxGTU9rXSwcfzEkO_v0brx05RYvJrH1bD=w163-h92-k-no"},{"name":"The Intan","type":"Museum","star":4.6,"address":"69 Joo Chiat Terrace","gmap_url":"https:\/\/www.google.com\/maps\/place\/The+Intan\/data=!4m7!3m6!1s0x31da1811b35745e1:0xa22e77539dba7667!8m2!3d1.3146307!4d103.9009827!16s%2Fg%2F1tdkv5qw!19sChIJ4UVXsxEY2jERZ3a6nVN3LqI?authuser=0&hl=en&rclk=1","image_url":"https:\/\/lh5.googleusercontent.com\/p\/AF1QipPe8Dq2pljmT3lKQ0TPGTjUx3u3OOuwNdZM8RZ-=w122-h92-k-no"},{"name":"Indian Heritage Centre","type":"Heritage museum","star":4.5,"address":"5 Campbell Ln","gmap_url":"https:\/\/www.google.com\/maps\/place\/Indian+Heritage+Centre\/data=!4m7!3m6!1s0x31da19b8dc4e2895:0xbb8d3e8ae15f79e1!8m2!3d1.3056816!4d103.8522606!16s%2Fg%2F11c52jv_k8!19sChIJlShO3LgZ2jER4Xlf4Yo-jbs?authuser=0&hl=en&rclk=1","image_url":"https:\/\/lh5.googleusercontent.com\/p\/AF1QipPiTOEfnPcibKIV-SnyYifWbTEs1kBv1IH7r00Y=w122-h92-k-no"},{"name":"Trickeye Singapore","type":"Museum","star":4.0,"address":"80 Siloso Road, Southside, Blk B, #01-04","gmap_url":"https:\/\/www.google.com\/maps\/place\/Trickeye+Singapore\/data=!4m7!3m6!1s0x31da1bfdc7bc1695:0x9fd51335af8b41f!8m2!3d1.258124!4d103.811537!16s%2Fg%2F1q69y5jh9!19sChIJlRa8x_0b2jERH7T4WjNR_Qk?authuser=0&hl=en&rclk=1","image_url":"https:\/\/lh5.googleusercontent.com\/p\/AF1QipOLVuPCL0W5ouMlA5oU7sqA2fhfmuYPmzThba-s=w138-h92-k-no"},{"name":"Fort Siloso","type":"War museum","star":4.5,"address":"Siloso Rd","gmap_url":"https:\/\/www.google.com\/maps\/place\/Fort+Siloso\/data=!4m7!3m6!1s0x31da1bf05ac7b659:0xf18f4c47e97982a4!8m2!3d1.259363!4d103.8086242!16zL20vMDRrZDZq!19sChIJWbbHWvAb2jERpIJ56UdMj_E?authuser=0&hl=en&rclk=1","image_url":"https:\/\/lh5.googleusercontent.com\/p\/AF1QipN8TCo6bXR7BmRClTsKCBSPqC9rSGUPREl6lOc7=w122-h92-k-no"},{"name":"NUS Museum","type":"Museum","star":4.6,"address":"50 Kent Ridge Cres","gmap_url":"https:\/\/www.google.com\/maps\/place\/NUS+Museum\/data=!4m7!3m6!1s0x31da1afa50000073:0x582a621ea6f4ff8a!8m2!3d1.3012948!4d103.7727162!16s%2Fm%2F0r4ylcj!19sChIJcwAAUPoa2jERiv_0ph5iKlg?authuser=0&hl=en&rclk=1","image_url":"https:\/\/lh5.googleusercontent.com\/p\/AF1QipOzSFRBe81QpraytHTSKGBylhJQXoheOWGF8GDy=w122-h92-k-no"},{"name":"Singapore Musical Box Museum","type":"Museum","star":4.8,"address":"19th- & 20th-century music box museum","gmap_url":"https:\/\/www.google.com\/maps\/place\/Singapore+Musical+Box+Museum\/data=!4m7!3m6!1s0x31da190d74dc8883:0xb5f134507dcf457b!8m2!3d1.2865077!4d103.8492213!16s%2Fg%2F11c3tj51wz!19sChIJg4jcdA0Z2jERe0XPfVA08bU?authuser=0&hl=en&rclk=1","image_url":"https:\/\/lh5.googleusercontent.com\/p\/AF1QipPjuH1gaG4L_TLw_giwiqyiIj7SkE4TwYkiEUkg=w138-h92-k-no"},{"name":"MINT Museum of Toys","type":"Toy museum","star":4.5,"address":"26 Seah St","gmap_url":"https:\/\/www.google.com\/maps\/place\/MINT+Museum+of+Toys\/data=!4m7!3m6!1s0x31da1912cd7bb05b:0xe03b75e5fec8d420!8m2!3d1.2963208!4d103.8546329!16s%2Fm%2F0g57081!19sChIJW7B7zRIZ2jERINTI_uV1O-A?authuser=0&hl=en&rclk=1","image_url":"https:\/\/lh5.googleusercontent.com\/p\/AF1QipOBCxilL5wuBwXUer4ZPjHoJCncKb6mMQG_zaJD=w137-h92-k-no"},{"name":"Hell's Museum","type":"Heritage museum","star":4.8,"address":"262 Pasir Panjang Rd","gmap_url":"https:\/\/www.google.com\/maps\/place\/Hell%27s+Museum\/data=!4m7!3m6!1s0x31da1bfae79514df:0xdeb4c0d02072760a!8m2!3d1.2839798!4d103.7818909!16s%2Fg%2F11p77682z3!19sChIJ3xSV5_ob2jERCnZyINDAtN4?authuser=0&hl=en&rclk=1","image_url":"https:\/\/lh5.googleusercontent.com\/p\/AF1QipPmuJbmWi9Q-0e7tqwjeMqVWMxlH2mncdcx7xZQ=w80-h106-k-no"},{"name":"National Museum of Singapore","type":"Museum","star":4.8,"address":"93 Stamford Rd","gmap_url":"https:\/\/www.google.com\/maps\/place\/National+Museum+of+Singapore\/data=!4m7!3m6!1s0x31da19a316b5b63b:0xa25eacf33afb537e!8m2!3d1.2967772!4d103.8487517!16s%2Fg%2F11tjbvtt10!19sChIJO7a1FqMZ2jERflP7OvOsXqI?authuser=0&hl=en&rclk=1","image_url":"https:\/\/lh5.googleusercontent.com\/p\/AF1QipP4agLT3sPYy8DFlUmf9sgPBB59qTMKTNQHdi6-=w122-h92-k-no"},{"name":"Reflections at Bukit Chandu","type":"War museum","star":4.5,"address":"31 - K Pepys Road","gmap_url":"https:\/\/www.google.com\/maps\/place\/Reflections+at+Bukit+Chandu\/data=!4m7!3m6!1s0x31da1bb9bc65b6f7:0x414081a42849aece!8m2!3d1.2797412!4d103.7942047!16s%2Fg%2F12hn3jxyw!19sChIJ97ZlvLkb2jERzq5JKKSBQEE?authuser=0&hl=en&rclk=1","image_url":"https:\/\/lh5.googleusercontent.com\/p\/AF1QipPXMLoxyToU7cJmoJecYs2hpo45FM83peIwXKvS=w138-h92-k-no"},{"name":"Children's Museum Singapore (formerly Singapore Philatelic Museum)","type":"Museum","star":4.6,"address":"23-B Coleman St","gmap_url":"https:\/\/www.google.com\/maps\/place\/Children%27s+Museum+Singapore+%28formerly+Singapore+Philatelic+Museum%29\/data=!4m7!3m6!1s0x31da19e386c61c8b:0x5c7413db55df28a6!8m2!3d1.2929269!4d103.8487246!16s%2Fg%2F11fp514dpw!19sChIJixzGhuMZ2jERpijfVdsTdFw?authuser=0&hl=en&rclk=1","image_url":"https:\/\/lh5.googleusercontent.com\/p\/AF1QipNTTdCYy6zXUxb0vc9Eb2cg5GEHnm9BBcZXp_ne=w157-h92-k-no"},{"name":"Singapore Air Force Museum","type":"Museum","star":4.4,"address":"400 Airport Rd","gmap_url":"https:\/\/www.google.com\/maps\/place\/Singapore+Air+Force+Museum\/data=!4m7!3m6!1s0x31da17c245555551:0x513008a535b27946!8m2!3d1.3467615!4d103.8993471!16s%2Fg%2F1tczbdm6!19sChIJUVVVRcIX2jERRnmyNaUIMFE?authuser=0&hl=en&rclk=1","image_url":"https:\/\/lh5.googleusercontent.com\/p\/AF1QipPoRIUxf96YB4-WL8tD5a3PIy4k9w4mKXKMclQg=w163-h92-k-no"},{"name":"Singapore Art Museum at Tanjong Pagar Distripark","type":"Art museum","star":4.5,"address":"39 Keppel Rd, #01-02","gmap_url":"https:\/\/www.google.com\/maps\/place\/Singapore+Art+Museum+at+Tanjong+Pagar+Distripark\/data=!4m7!3m6!1s0x31da190b4b2f2d3d:0x301402de71935aba!8m2!3d1.2719533!4d103.836752!16s%2Fg%2F11p6d57t4c!19sChIJPS0vSwsZ2jERulqTcd4CFDA?authuser=0&hl=en&rclk=1","image_url":"https:\/\/lh5.googleusercontent.com\/p\/AF1QipOvLMQnWB2Vfw7XVtb68dxwKRYaoV6pVr6KWcd9=w122-h92-k-no"},{"name":"Civil Defence Heritage Gallery","type":"Historical place museum","star":4.6,"address":"62 Hill St","gmap_url":"https:\/\/www.google.com\/maps\/place\/Civil+Defence+Heritage+Gallery\/data=!4m7!3m6!1s0x31da19a11836343f:0x7e8321f6e2e4449d!8m2!3d1.2919146!4d103.849146!16s%2Fg%2F1tcvlsxd!19sChIJPzQ2GKEZ2jERnUTk4vYhg34?authuser=0&hl=en&rclk=1","image_url":"https:\/\/lh5.googleusercontent.com\/p\/AF1QipPOgpcsVEm3OAeGBKzx6D6Yrf6E5T7bimyOW3Od=w122-h92-k-no"},{"name":"Lee Kong Chian Natural History Museum, Singapore","type":"Natural history museum","star":4.6,"address":"2 Conservatory Dr","gmap_url":"https:\/\/www.google.com\/maps\/place\/Lee+Kong+Chian+Natural+History+Museum,+Singapore\/data=!4m7!3m6!1s0x31da1af649a3c895:0xf1cf69b90fc29d19!8m2!3d1.3014156!4d103.7736549!16s%2Fm%2F0134gjbh!19sChIJlcijSfYa2jERGZ3CD7lpz_E?authuser=0&hl=en&rclk=1","image_url":"https:\/\/lh5.googleusercontent.com\/p\/AF1QipPO7njxrL3PWUpQNEv2lmH_LgqfbBk6_wOV_Wnf=w122-h92-k-no"},{"name":"Changi Chapel & Museum","type":"War museum","star":4.4,"address":"1000 Upper Changi Rd N","gmap_url":"https:\/\/www.google.com\/maps\/place\/Changi+Chapel+%26+Museum\/data=!4m7!3m6!1s0x31da3cf7eac10109:0x8ece052eb785a8ab!8m2!3d1.362212!4d103.974025!16s%2Fm%2F03hnk16!19sChIJCQHB6vc82jERq6iFty4Fzo4?authuser=0&hl=en&rclk=1","image_url":"https:\/\/lh5.googleusercontent.com\/p\/AF1QipMeEZTX76rRWUV2J05oH3O71-y7z_HiCJdU8RJ2=w122-h92-k-no"},{"name":"Friends of the Museums","type":"Museum","star":4.5,"address":"61 Stamford Rd","gmap_url":"https:\/\/www.google.com\/maps\/place\/Friends+of+the+Museums\/data=!4m7!3m6!1s0x31da19a3f0bbd1a5:0x4e0304281482f15f!8m2!3d1.2943555!4d103.8502032!16s%2Fg%2F1ptwj1gpd!19sChIJpdG78KMZ2jERX_GCFCgEA04?authuser=0&hl=en&rclk=1","image_url":"https:\/\/lh5.googleusercontent.com\/p\/AF1QipP42MBVQWUZvdjdLX0aOVZjbSwTgq3JxWp4qB06=w189-h92-k-no"},{"name":"Fort Canning Heritage Gallery","type":"Museum","star":4.5,"address":"5 Cox Terrace","gmap_url":"https:\/\/www.google.com\/maps\/place\/Fort+Canning+Heritage+Gallery\/data=!4m7!3m6!1s0x31da19ab633fef0b:0xdf1701b560b9e2ec!8m2!3d1.2949763!4d103.8468403!16s%2Fg%2F11tcd9g261!19sChIJC-8_Y6sZ2jER7OK5YLUBF98?authuser=0&hl=en&rclk=1","image_url":"https:\/\/lh5.googleusercontent.com\/p\/AF1QipOChGtJGivjTb6NNzS_4mu5mzEZPl8e9zYQmdqB=w122-h92-k-no"},{"name":"Katong Antique House","type":"Local history museum","star":4.3,"address":"Singapore","gmap_url":"https:\/\/www.google.com\/maps\/place\/Katong+Antique+House\/data=!4m7!3m6!1s0x31da18734a6738b5:0xd112392ca1698dd6!8m2!3d1.3071999!4d103.9071196!16s%2Fg%2F1v9l88dt!19sChIJtThnSnMY2jER1o1poSw5EtE?authuser=0&hl=en&rclk=1","image_url":"https:\/\/lh5.googleusercontent.com\/p\/AF1QipOdTwdaDwZrUBKUsoPOvzBCNoXEBYm6XPDxooSr=w122-h92-k-no"},{"name":"Kreta Ayer Heritage Gallery","type":"Museum","star":4.5,"address":"28 Kreta Ayer Rd","gmap_url":"https:\/\/www.google.com\/maps\/place\/Kreta+Ayer+Heritage+Gallery\/data=!4m7!3m6!1s0x31da1920e6376939:0xec845041b4fa2754!8m2!3d1.2807977!4d103.8427617!16s%2Fg%2F11h_y460h1!19sChIJOWk35iAZ2jERVCf6tEFQhOw?authuser=0&hl=en&rclk=1","image_url":"https:\/\/lh5.googleusercontent.com\/p\/AF1QipNkvGwe04QMVK2BRChF_xknvjDfm8N6rfCMhLgY=w145-h92-k-no"},{"name":"Singapore Maritime Gallery","type":"Maritime museum","star":4.4,"address":"31 Marina Coastal Dr, Level 2","gmap_url":"https:\/\/www.google.com\/maps\/place\/Singapore+Maritime+Gallery\/data=!4m7!3m6!1s0x31da191f43e3f6c9:0xe9030beb89091c07!8m2!3d1.2710567!4d103.8632231!16s%2Fg%2F11cn8wppyd!19sChIJyfbjQx8Z2jERBxwJiesLA-k?authuser=0&hl=en&rclk=1","image_url":"https:\/\/lh5.googleusercontent.com\/p\/AF1QipP9gLqA-m_zd-XqosqO4VsivfFBIca2qJfdP8PL=w163-h92-k-no"},{"name":"teamLab Future World","type":"Museum","star":4.4,"address":"6 Bayfront Ave","gmap_url":"https:\/\/www.google.com\/maps\/place\/teamLab+Future+World\/data=!4m7!3m6!1s0x31da1906562499b7:0x8680b70e6c6d6193!8m2!3d1.2862784!4d103.8592687!16s%2Fg%2F11c51w49lz!19sChIJt5kkVgYZ2jERk2FtbA63gIY?authuser=0&hl=en&rclk=1","image_url":"https:\/\/lh5.googleusercontent.com\/p\/AF1QipMuTGX6NsWLF49E7bjeWDBAEnFzlcs3YzeqXAvs=w122-h92-k-no"},{"name":"Click art museum","type":"Museum","star":4.4,"address":"8D Jln Kledek","gmap_url":"https:\/\/www.google.com\/maps\/place\/Click+art+museum\/data=!4m7!3m6!1s0x31da19b728d80ed9:0xc9fe3f39719542fb!8m2!3d1.3036766!4d103.8590737!16s%2Fg%2F11dfjsh1nh!19sChIJ2Q7YKLcZ2jER-0KVcTk__sk?authuser=0&hl=en&rclk=1","image_url":"https:\/\/lh5.googleusercontent.com\/p\/AF1QipN5isQYzUV7NxQq2hfK7to-toijx1igItHcO42W=w122-h92-k-no"},{"name":"SBG Heritage Museum","type":"Heritage museum","star":4.4,"address":"1 Cluny Road","gmap_url":"https:\/\/www.google.com\/maps\/place\/SBG+Heritage+Museum\/data=!4m7!3m6!1s0x31da1a1f6929d635:0xb07a31fbab6f4318!8m2!3d1.3086915!4d103.8176093!16s%2Fg%2F11byyqxf82!19sChIJNdYpaR8a2jERGENvq_sxerA?authuser=0&hl=en&rclk=1","image_url":"https:\/\/lh5.googleusercontent.com\/p\/AF1QipP5yP_dEFi0ZeA3RB70oPioGjSWznPalTHQCPtj=w138-h92-k-no"},{"name":"MOE Heritage Centre","type":"Heritage museum","star":4.5,"address":"565 Balestier Rd, Block C, Level 1","gmap_url":"https:\/\/www.google.com\/maps\/place\/MOE+Heritage+Centre\/data=!4m7!3m6!1s0x31da1a40abcf9e23:0xa654727479cc25a7!8m2!3d1.3257583!4d103.8449253!16s%2Fg%2F11b90m3r0s!19sChIJI57Pq0Aa2jERpyXMeXRyVKY?authuser=0&hl=en&rclk=1","image_url":"https:\/\/lh5.googleusercontent.com\/p\/AF1QipMi_Z60UCThnKXoEhw9FFFvsPMlGrksk9EDV1lb=w138-h92-k-no"},{"name":"Singapore Sports Museum","type":"Museum","star":4.6,"address":"6 Stadium Walk","gmap_url":"https:\/\/www.google.com\/maps\/place\/Singapore+Sports+Museum\/data=!4m7!3m6!1s0x31da184c25d137e9:0xb0d1c112324599cd!8m2!3d1.3013548!4d103.8736219!16s%2Fm%2F02qztg7!19sChIJ6TfRJUwY2jERzZlFMhLB0bA?authuser=0&hl=en&rclk=1","image_url":"https:\/\/lh5.googleusercontent.com\/p\/AF1QipNyLrHTg0UPp812EogOaQkSlP4ecKiZKBpaPIGX=w122-h92-k-no"},{"name":"Former Ford Factory","type":"War museum","star":4.5,"address":"351 Upper Bukit Timah Rd","gmap_url":"https:\/\/www.google.com\/maps\/place\/Former+Ford+Factory\/data=!4m7!3m6!1s0x31da105a2b97cc4d:0x4d1a4bd9b41f3132!8m2!3d1.3527256!4d103.7688464!16zL20vMGJic2M3!19sChIJTcyXK1oQ2jERMjEftNlLGk0?authuser=0&hl=en&rclk=1","image_url":"https:\/\/lh5.googleusercontent.com\/p\/AF1QipO2Zqy-_AFpmkU9P8NzFHSK17zEpecknZkWxQCM=w122-h92-k-no"},{"name":"Red Dot Design Museum","type":"Museum","star":4.4,"address":"11 Marina Blvd","gmap_url":"https:\/\/www.google.com\/maps\/place\/Red+Dot+Design+Museum\/data=!4m7!3m6!1s0x31da1912c68752ab:0xfafa51da63b1f3ed!8m2!3d1.2801289!4d103.8562179!16s%2Fg%2F1tdgry0h!19sChIJq1KHxhIZ2jER7fOxY9pR-vo?authuser=0&hl=en&rclk=1","image_url":"https:\/\/lh5.googleusercontent.com\/p\/AF1QipNL1MB9FOkspGLjBYRNw0KZqFouLtFqT_CMq5NT=w136-h92-k-no"},{"name":"Police Heritage Centre","type":"Cultural center","star":4.4,"address":"28 Irrawaddy Rd","gmap_url":"https:\/\/www.google.com\/maps\/place\/Police+Heritage+Centre\/data=!4m7!3m6!1s0x31da19e09aaaaab3:0x9a3260c49fde108d!8m2!3d1.324142!4d103.845271!16s%2Fg%2F1tdx66zc!19sChIJs6qqmuAZ2jERjRDen8RgMpo?authuser=0&hl=en&rclk=1","image_url":"https:\/\/lh5.googleusercontent.com\/p\/AF1QipM8bZSlW_kraz3TsU_k3RBteWxswPo4-Odltlo=w163-h92-k-no"},{"name":"The Gem Museum","type":"Museum","star":4.8,"address":"9 Perak Rd","gmap_url":"https:\/\/www.google.com\/maps\/place\/The+Gem+Museum\/data=!4m7!3m6!1s0x31da19a4b9b0d731:0x73aee4dfb4d207c3!8m2!3d1.304514!4d103.853039!16s%2Fg%2F11b8tdg1y2!19sChIJMdewuaQZ2jERwwfStN_krnM?authuser=0&hl=en&rclk=1","image_url":"https:\/\/lh5.googleusercontent.com\/p\/AF1QipNDLtxccdyGRWkgLDfE13SYn8Ypk4bRFgDLfHgV=w138-h92-k-no"},{"name":"Singapore Cable Car Museum","type":"Museum","star":5.0,"address":"Singapore","gmap_url":"https:\/\/www.google.com\/maps\/place\/Singapore+Cable+Car+Museum\/data=!4m7!3m6!1s0x31da1bf6c4b941b3:0xb81b70eba44bc5b0!8m2!3d1.2713064!4d103.8193878!16s%2Fg%2F11ndyk4scy!19sChIJs0G5xPYb2jERsMVLpOtwG7g?authuser=0&hl=en&rclk=1","image_url":"https:\/\/lh5.googleusercontent.com\/p\/AF1QipM2m9k1HVhIEbnXUobSSEx3T1SsOCm4Wtn6jLVD=w80-h106-k-no"},{"name":"Peranakan Gallery (Terminal 4 Changi Airport)","type":"Heritage museum","star":4.7,"address":"Singapore","gmap_url":"https:\/\/www.google.com\/maps\/place\/Peranakan+Gallery+%28Terminal+4+Changi+Airport%29\/data=!4m7!3m6!1s0x31da3d1b55703f0f:0x4085962d26e4631c!8m2!3d1.3384742!4d103.9834851!16s%2Fg%2F11g4cgj093!19sChIJDz9wVRs92jERHGPkJi2WhUA?authuser=0&hl=en&rclk=1","image_url":"https:\/\/lh5.googleusercontent.com\/p\/AF1QipNiiI0LJE1qBk9SHQI9wVGHJ_CgX7XZR9kgmFoc=w138-h92-k-no"},{"name":"Geylang Serai Heritage Gallery","type":"Heritage museum","star":4.5,"address":"1 Engku Aman, #01-05 Wisma, Turn","gmap_url":"https:\/\/www.google.com\/maps\/place\/Geylang+Serai+Heritage+Gallery\/data=!4m7!3m6!1s0x31da19303f7b8be7:0x10763a3925814bfb!8m2!3d1.3166871!4d103.897084!16s%2Fg%2F11fm5x57py!19sChIJ54t7PzAZ2jER-0uBJTk6dhA?authuser=0&hl=en&rclk=1","image_url":"https:\/\/lh5.googleusercontent.com\/p\/AF1QipMCFGiLKYthtj0qyQpVUCiZ1rj9BHMvwXq2KZqC=w122-h92-k-no"}]